rudleg/__init__.py
rudleg/_cli.py
rudleg/abstract_packet.py
rudleg/animate.py
rudleg/camera.py
rudleg/exceptions.py
rudleg/johnson.py
rudleg/physic2d.py
rudleg/_core_magic/CodeTemplateAndFunction.py
rudleg/_core_magic/DebugManager.py
rudleg/_core_magic/ExecuteCommand.py
rudleg/_core_magic/TheMainGame.py
rudleg/_core_magic/__init__.py
rudleg/_core_magic/build.json
rudleg/stuff/stuff/RUDLIcon.png
rudleg/stuff/stuff/icon.ico
rudleg/stuff/stuff/icon.png
rudleg/stuff/stuff/that_man.png
rudleg/stuff/stuff/tiles-4.png
rudleg/textures/__init__.py
rudleg/textures/texture.py
rudleg/ui_interface/__init__.py
rudleg/ui_interface/button_type.py
rudleg/ui_interface/user_type.py
rudleg-0.1.2.2.dist-info/licenses/LICENSE
rudleg-0.1.2.2.dist-info/METADATA
rudleg-0.1.2.2.dist-info/WHEEL
rudleg-0.1.2.2.dist-info/entry_points.txt
rudleg-0.1.2.2.dist-info/top_level.txt
rudleg-0.1.2.2.dist-info/RECORD
