Metadata-Version: 2.4
Name: rudleg
Version: 0.1.2.2
Summary: RUDLeg - The RUDL Engine, 2D game framework.
Author: TheDreadMatrix
License:                                  Apache License
Requires-Python: >=3.8
License-File: LICENSE
Requires-Dist: pygame-ce<2.6,>=2.5
Requires-Dist: moderngl<6.5,>=5.10
Requires-Dist: pyglm>=0.1
Requires-Dist: Pillow<11.0,>=10.0
Dynamic: license-file
